CodingDrone/__init__.py
CodingDrone/__main__.py
CodingDrone/crc.py
CodingDrone/drone.py
CodingDrone/protocol.py
CodingDrone/receiver.py
CodingDrone/storage.py
CodingDrone/system.py
CodingDrone/update.py
CodingDrone/tools/__init__.py
CodingDrone/tools/parser.py
CodingDrone/tools/update.py
CodingDrone-1.0.4.dist-info/LICENSE
CodingDrone-1.0.4.dist-info/METADATA
CodingDrone-1.0.4.dist-info/WHEEL
CodingDrone-1.0.4.dist-info/top_level.txt
CodingDrone-1.0.4.dist-info/RECORD
