Metadata-Version: 2.1
Name: CodingDrone
Version: 1.0.4
Summary: Library for CodingDrone.
Home-page: https://imssam.me/shop/view.php?index_no=25
Author: v
Author-email: devdrone@aluxonline.com
License-File: LICENSE
Requires-Dist: pyserial >=3.4
Requires-Dist: numpy >=1.15.4
Requires-Dist: colorama >=0.4.0
